asyncio_socks_server/__init__.py
asyncio_socks_server/__main__.py
asyncio_socks_server/__version__.py
asyncio_socks_server/app.py
asyncio_socks_server/authenticators.py
asyncio_socks_server/config.py
asyncio_socks_server/exceptions.py
asyncio_socks_server/logger.py
asyncio_socks_server/protocols.py
asyncio_socks_server/proxyman.py
asyncio_socks_server/utils.py
asyncio_socks_server/values.py
asyncio_socks_server-0.3.0.dist-info/entry_points.txt
asyncio_socks_server-0.3.0.dist-info/LICENSE
asyncio_socks_server-0.3.0.dist-info/WHEEL
asyncio_socks_server-0.3.0.dist-info/METADATA
asyncio_socks_server-0.3.0.dist-info/RECORD
